LICENSE.md
README.md
setup.cfg
setup.py
src/pintle/__init__.py
src/pintle/atomic_interval.py
src/pintle/bounds.py
src/pintle/exception.py
src/pintle/intervals.py
src/pintle/patterns.py
src/pintle.egg-info/PKG-INFO
src/pintle.egg-info/SOURCES.txt
src/pintle.egg-info/dependency_links.txt
src/pintle.egg-info/requires.txt
src/pintle.egg-info/top_level.txt
src/pintle/algorithms/__init__.py
src/pintle/algorithms/binary_search_interval.py
src/pintle/colors/__init__.py
src/pintle/colors/colors.py