Metadata-Version: 2.1
Name: pintle
Version: 0.0.3
Summary: Convenient tool for working with intervals
Home-page: UNKNOWN
Author: Nico Krokhmal
Author-email: krokhmal11@gmail.com
License: UNKNOWN
Keywords: intervals,math
Platform: UNKNOWN
Classifier: Programming Language :: Python :: 3
Classifier: Operating System :: OS Independent
Requires-Python: >=3.6
License-File: LICENSE.md
